{"cameraMode":{"drawMode":0,"name":"Shaded","section":"Shading Mode"},"sceneLighting":false,"audioPlay":false,"sceneViewState":{"m_AlwaysRefresh":false,"showFog":true,"showSkybox":false,"showFlares":true,"showImageEffects":true,"showParticleSystems":true,"showVisualEffectGraphs":true,"m_FxEnabled":true},"in2DMode":false,"pivot":{"x":-338.44775390625,"y":220.59471130371095,"z":-164.7217254638672},"rotation":{"x":-0.02971140667796135,"y":0.9420676231384277,"z":-0.32267993688583376,"w":-0.08672839403152466},"size":10.0,"orthographic":false}